{
  "project_info": {
    "project_number": "92899643813",
    "firebase_url": "https://ng-gram.firebaseio.com",
    "project_id": "ng-gram",
    "storage_bucket": "ng-gram.appspot.com"
  },
  "client": [
    {
      "client_info": {
        "mobilesdk_app_id": "1:92899643813:android:aeac85f51dbd0426",
        "android_client_info": {
          "package_name": "com.jorgeucano.nggram"
        }
      },
      "oauth_client": [
        {
          "client_id": "92899643813-ugmjh7h0li63u0e1t5712ajq3g2udonr.apps.googleusercontent.com",
          "client_type": 3
        }
      ],
      "api_key": [
        {
          "current_key": "AIzaSyBWkDqyHGCMY1xAHmEz1nkWJ0amUlCujeM"
        }
      ],
      "services": {
        "analytics_service": {
          "status": 1
        },
        "appinvite_service": {
          "status": 1,
          "other_platform_oauth_client": []
        },
        "ads_service": {
          "status": 2
        }
      }
    }
  ],
  "configuration_version": "1"
}